neo4py/__init__.py
neo4py/main.py
neo4py_atharnaveed-1.0.2b0.dist-info/LICENSE
neo4py_atharnaveed-1.0.2b0.dist-info/METADATA
neo4py_atharnaveed-1.0.2b0.dist-info/WHEEL
neo4py_atharnaveed-1.0.2b0.dist-info/top_level.txt
neo4py_atharnaveed-1.0.2b0.dist-info/RECORD
