Metadata-Version: 2.1
Name: neo4py-atharnaveed
Version: 1.0.2b0
Summary: Neo4py is a better alternative to py2neo.
Author-email: Athar Naveed <asphaltlegends24@gmail.com>
Project-URL: Homepage, https://github.com/Athar-Naveed/neo4py
Classifier: Programming Language :: Python :: 3
Classifier: License :: OSI Approved :: Apache Software License
Classifier: Operating System :: OS Independent
Requires-Python: >=3.8
License-File: LICENSE
